MANIFEST.in
setup.cfg
setup.py
src/nust/__init__.py
src/nust/body.py
src/nust/nust.conf
src/nust/utils.py
src/nust.egg-info/PKG-INFO
src/nust.egg-info/SOURCES.txt
src/nust.egg-info/dependency_links.txt
src/nust.egg-info/entry_points.txt
src/nust.egg-info/not-zip-safe
src/nust.egg-info/top_level.txt