Metadata-Version: 1.0
Name: nust
Version: dev-20110623-01
Summary: This is a nginx's config parser and starter for uwsgi workers (tested on uwsgi 0.9.8)
Home-page: http://dev.telemost.net/wiki/nginx_uwsgi_starter
Author: Sergey Vasilenko
Author-email: sv@makeworld.ru
License: GPL
Keywords: nginx uwsgi starter
Platform: All
Classifier: Environment :: Console
Classifier: Operating System :: Unix
Classifier: Programming Language :: Python
Classifier: Natural Language :: Russian
Classifier: Development Status :: 4 - Beta
Classifier: Topic :: Internet :: WWW/HTTP :: WSGI
